JiraTracker/Exceptions.py
JiraTracker/GitHistoryParser.py
JiraTracker/HistoryEvent.py
JiraTracker/HistoryLine.py
JiraTracker/JiraApi.py
JiraTracker/JiraTracker.py
JiraTracker/Project.py
JiraTracker/Settings.py
JiraTracker/Tracker.py
JiraTracker/__init__.py
jiratracker-1.0.2.dist-info/DESCRIPTION.rst
jiratracker-1.0.2.dist-info/METADATA
jiratracker-1.0.2.dist-info/RECORD
jiratracker-1.0.2.dist-info/WHEEL
jiratracker-1.0.2.dist-info/metadata.json
jiratracker-1.0.2.dist-info/top_level.txt
