Metadata-Version: 2.0
Name: jiratracker
Version: 1.0.2
Summary: Automatically logs development time to Jira based on Git checkout history
Home-page: https://github.com/dor-denis/JiraTracker
Author: Denys Dorofeiev
Author-email: dor.denis.de@gmail.com
License: UNKNOWN
Keywords: jira log track
Platform: UNKNOWN
Requires-Dist: requests
Requires-Dist: pyyaml
